ghostrade/agents/__init__.py
ghostrade/agents/base.py
ghostrade/agents/claude.py
ghostrade/agents/openai.py
ghostrade/brokers/__init__.py
ghostrade/brokers/alpaca.py
ghostrade/brokers/base.py
ghostrade-0.1.0.dist-info/LICENSE
ghostrade-0.1.0.dist-info/METADATA
ghostrade-0.1.0.dist-info/WHEEL
ghostrade-0.1.0.dist-info/top_level.txt
ghostrade-0.1.0.dist-info/RECORD
