Metadata-Version: 2.1
Name: ghostrade
Version: 0.1.0
Summary: An agentic trading framework
Author-email: jacob weiss <jaweiss2305@gmail.com>
License: Apache License
Project-URL: Homepage, https://github.com/jaweiss/ghostrade
Project-URL: Bug Tracker, https://github.com/jaweiss/ghostrade/issues
Classifier: Programming Language :: Python :: 3
Classifier: License :: OSI Approved :: MIT License
Classifier: Operating System :: OS Independent
Requires-Python: >=3.10
License-File: LICENSE
Requires-Dist: pandas
